Metadata-Version: 2.1
Name: calculatrice
Version: 0.0.0
Summary: calculatrice
Home-page: https://github.com/fedjyst/calculatrice.git
Author: Exzard Jean Abellard et Payen Sterlin Myfedjy 
Classifier: Development Status :: 3 - Alpha
Classifier: Intended Audience :: Developers
Classifier: License :: OSI Approved :: MIT License
Classifier: Programming Language :: Python :: 3.6
Classifier: Programming Language :: Python :: 3.7
Classifier: Programming Language :: Python :: 3.8
Classifier: Programming Language :: Python :: 3.9
